breez_sdk/__init__.py
breez_sdk/breez_sdk.py
breez_sdk/breez_sdk_bindings.dll
breez_sdk/msvcp140.dll
breez_sdk/vcruntime140.dll
breez_sdk/vcruntime140_1.dll
breez_sdk-0.8.0.dist-info/METADATA
breez_sdk-0.8.0.dist-info/WHEEL
breez_sdk-0.8.0.dist-info/top_level.txt
breez_sdk-0.8.0.dist-info/RECORD
